ghoclient/__init__.py
ghoclient/cli.py
ghoclient/ghoclient.py
ghoclient/index.py
ghoclient-1.0.3.dist-info/AUTHORS.rst
ghoclient-1.0.3.dist-info/LICENSE
ghoclient-1.0.3.dist-info/METADATA
ghoclient-1.0.3.dist-info/WHEEL
ghoclient-1.0.3.dist-info/entry_points.txt
ghoclient-1.0.3.dist-info/top_level.txt
ghoclient-1.0.3.dist-info/RECORD
