Metadata-Version: 2.1
Name: ghoclient
Version: 1.0.3
Summary: Python client to the WHO Global Health Observatory.
Home-page: https://github.com/fccoelho/ghoclient
Author: Flávio Codeço Coelho
Author-email: fccoelho@gmail.com
License: MIT license
Keywords: ghoclient
Platform: UNKNOWN
Classifier: Development Status :: 2 - Pre-Alpha
Classifier: Intended Audience :: Developers
Classifier: License :: OSI Approved :: MIT License
Classifier: Natural Language :: English
Classifier: Programming Language :: Python :: 3
Classifier: Programming Language :: Python :: 3.5
Classifier: Programming Language :: Python :: 3.6
Classifier: Programming Language :: Python :: 3.7
Classifier: Programming Language :: Python :: 3.8
Requires-Python: >=3.5
Requires-Dist: Click (>=7.0)
